fugle_realtime/__init__.py
fugle_realtime/base_client.py
fugle_realtime/http_client/__init__.py
fugle_realtime/http_client/historical.py
fugle_realtime/http_client/http_client.py
fugle_realtime/http_client/intraday.py
fugle_realtime/websocket_client/__init__.py
fugle_realtime/websocket_client/intraday.py
fugle_realtime/websocket_client/websocket_client.py
fugle_realtime/websocket_client/ws.py
fugle_realtime-0.4.2.dist-info/LICENSE
fugle_realtime-0.4.2.dist-info/WHEEL
fugle_realtime-0.4.2.dist-info/METADATA
fugle_realtime-0.4.2.dist-info/RECORD
