Metadata-Version: 2.1
Name: fugle-realtime
Version: 0.4.2
Summary: Fugle Realtime API client library for Python
Home-page: https://github.com/fugle-dev/fugle-realtime-py#readme
License: MIT
Keywords: fugle,realtime,stock
Author: Fortuna Intelligence Co., Ltd.
Author-email: development@fugle.tw
Requires-Python: >=3.7,<4.0
Classifier: License :: OSI Approved :: MIT License
Classifier: Programming Language :: Python :: 3
Classifier: Programming Language :: Python :: 3.7
Classifier: Programming Language :: Python :: 3.8
Classifier: Programming Language :: Python :: 3.9
Requires-Dist: requests (>=2.26.0,<3.0.0)
Requires-Dist: websocket-client (>=1.2.1,<2.0.0)
Project-URL: Documentation, https://developer.fugle.tw
Project-URL: Repository, https://github.com/fugle-dev/fugle-realtime-py
